zoltraak/__init__.py
zoltraak/cli.py
zoltraak/converter.py
zoltraak/md_generator.py
zoltraak/grimoires/architect/architect.md
zoltraak/grimoires/architect/architect_detail.md
zoltraak/grimoires/architect/architect_detail_dir.md
zoltraak/grimoires/architect/architect_functor.md
zoltraak/grimoires/compiler/biz_consult copy.md
zoltraak/grimoires/compiler/biz_consult.md
zoltraak/grimoires/compiler/biz_consult2.md
zoltraak/grimoires/compiler/book_lecture_main.md
zoltraak/grimoires/compiler/book_lecture_quiz.md
zoltraak/grimoires/compiler/dev_akirapp.md
zoltraak/grimoires/compiler/dev_front.md
zoltraak/grimoires/compiler/dev_func.md
zoltraak/grimoires/compiler/dev_obj.md
zoltraak/grimoires/compiler/dev_obj_lisp.md
zoltraak/grimoires/compiler/dev_obj_lisp_g.md
zoltraak/grimoires/compiler/dev_obj_lisp_g_base64.md
zoltraak/grimoires/compiler/dev_obj_mermaid.md
zoltraak/grimoires/compiler/dev_react_fastapi.md
zoltraak/grimoires/compiler/encode_lisp.md
zoltraak/grimoires/compiler/front_faq.md
zoltraak/grimoires/compiler/front_hp.md
zoltraak/grimoires/compiler/general_def.md
zoltraak/grimoires/compiler/general_reqdef.md
zoltraak/grimoires/compiler/ref_create_directory.py
zoltraak/grimoires/developer/dev_csharp.md
zoltraak/grimoires/developer/dev_python.md
zoltraak/grimoires/encryption/emoji.md
zoltraak/grimoires/formatter/default.md
zoltraak/grimoires/formatter/md_comment.md
zoltraak/grimoires/formatter/md_comment_ar.md
zoltraak/grimoires/formatter/md_comment_bn.md
zoltraak/grimoires/formatter/md_comment_de.md
zoltraak/grimoires/formatter/md_comment_en.md
zoltraak/grimoires/formatter/md_comment_es.md
zoltraak/grimoires/formatter/md_comment_fa.md
zoltraak/grimoires/formatter/md_comment_fr.md
zoltraak/grimoires/formatter/md_comment_hi.md
zoltraak/grimoires/formatter/md_comment_hu.md
zoltraak/grimoires/formatter/md_comment_id.md
zoltraak/grimoires/formatter/md_comment_it.md
zoltraak/grimoires/formatter/md_comment_ko.md
zoltraak/grimoires/formatter/md_comment_lang.md
zoltraak_celsius-0.1.25.dist-info/LICENSE
zoltraak_celsius-0.1.25.dist-info/METADATA
zoltraak_celsius-0.1.25.dist-info/WHEEL
zoltraak_celsius-0.1.25.dist-info/entry_points.txt
zoltraak_celsius-0.1.25.dist-info/top_level.txt
zoltraak_celsius-0.1.25.dist-info/RECORD
