Metadata-Version: 2.1
Name: zoltraak_celsius
Version: 0.1.25
Classifier: Development Status :: 4 - Beta
Classifier: Intended Audience :: Developers
Classifier: Topic :: Utilities
License-File: LICENSE
Requires-Dist: openai
Requires-Dist: anthropic
Requires-Dist: groq
Requires-Dist: python-dotenv
Requires-Dist: pyperclip
Requires-Dist: wheel
Requires-Dist: art
Requires-Dist: loguru
